hypertrain/__init__.py
hypertrain/exceptions.py
hypertrain/utilities.py
hypertrain/controllers/__init__.py
hypertrain/controllers/hyperparameter_study.py
hypertrain/controllers/hyperparameter_study_tuning.py
hypertrain/controllers/trial.py
hypertrain/controllers/trial_log_callback.py
hypertrain/controllers/trial_logging.py
hypertrain/datamodel/__init__.py
hypertrain/datamodel/base.py
hypertrain/datamodel/artifact/__doc__.py
hypertrain/datamodel/artifact/__init__.py
hypertrain/datamodel/artifact/methods.py
hypertrain/datamodel/hyperparameter_study/__doc__.py
hypertrain/datamodel/hyperparameter_study/__init__.py
hypertrain/datamodel/trial/__doc__.py
hypertrain/datamodel/trial/__init__.py
hypertrain/datamodel/trial/methods.py
hypertrain/flavor/__init__.py
hypertrain/flavor/pytorch/__init__.py
hypertrain/flavor/sklearn/__init__.py
hypertrain/flavor/tensorflow/__init__.py
hypertrain/flavor/xgboost/__init__.py
hypertrain/meta/__init__.py
hypertrain/meta/trial.py
hypertrain/meta/interface/__init__.py
hypertrain/meta/interface/manifest.py
hypertrain-0.1.0.dist-info/METADATA
hypertrain-0.1.0.dist-info/WHEEL
hypertrain-0.1.0.dist-info/top_level.txt
hypertrain-0.1.0.dist-info/RECORD
